pyerk/__init__.py
pyerk/auxiliary.py
pyerk/builtin_entities.py
pyerk/core.py
pyerk/erkloader.py
pyerk/io.py
pyerk/rdfstack.py
pyerk/release.py
pyerk/reportgenerator.py
pyerk/ruleengine.py
pyerk/script.py
pyerk/settings.py
pyerk/visualization.py
pyerk/templates/base.css
pyerk/templates/l1_rule-application-report-stm.html
pyerk/templates/report-template.tex
pyerk/templates/rule-application-report-page.html
pyerk-0.9.0.dist-info/LICENSE
pyerk-0.9.0.dist-info/METADATA
pyerk-0.9.0.dist-info/WHEEL
pyerk-0.9.0.dist-info/entry_points.txt
pyerk-0.9.0.dist-info/top_level.txt
pyerk-0.9.0.dist-info/RECORD
