Metadata-Version: 2.1
Name: pyerk
Version: 0.9.0
Summary: Python based 'Easy Representation of Knowledge' (pyERK)
Author-email: Carsten Knoll <firstname.lastname@posteo.de>
License: GNU General Public License v3 (GPLv3)
Project-URL: Homepage, https://github.com/ackrep-org/pyerk-core/
Classifier: Development Status :: 3 - Alpha
Classifier: Intended Audience :: Developers
Classifier: Programming Language :: Python :: 3
Requires-Python: >=3.8
License-File: LICENSE
Requires-Dist: pyyaml
Requires-Dist: ipydex
Requires-Dist: colorama
Requires-Dist: rdflib
Requires-Dist: addict
Requires-Dist: networkx
Requires-Dist: nxv
Requires-Dist: jinja2
Requires-Dist: gitpython
Requires-Dist: pydantic
Requires-Dist: tomli >=1.1.0 ; python_version < "3.11"
